pw/__init__.py
pw/__main__.py
pw/_gpg.py
pw/store.py
pw-0.14.1.dist-info/LICENSE
pw-0.14.1.dist-info/METADATA
pw-0.14.1.dist-info/WHEEL
pw-0.14.1.dist-info/entry_points.txt
pw-0.14.1.dist-info/RECORD
