Metadata-Version: 2.1
Name: pw
Version: 0.14.1
Summary: Search in GPG-encrypted password file.
Home-page: https://github.com/catch22/pw
License: MIT
Author: Michael Walter
Author-email: michael.walter@gmail.com
Requires-Python: >=3.9,<4.0
Classifier: Environment :: Console
Classifier: License :: OSI Approved :: MIT License
Classifier: Programming Language :: Python :: 3
Classifier: Programming Language :: Python :: 3.9
Classifier: Programming Language :: Python :: 3.10
Classifier: Programming Language :: Python :: 3.11
Classifier: Programming Language :: Python :: 3.12
Requires-Dist: click (>=8.1.7,<9.0.0)
Requires-Dist: colorama (>=0.4.6,<0.5.0)
Requires-Dist: pyperclip (>=1.8.2,<2.0.0)
